{"_class":"document","do_objectID":"19346EF0-BAA2-4694-9538-DF54D93542BA","assets":{"_class":"assetCollection","colors":[],"gradients":[],"imageCollection":{"_class":"imageCollection","images":{}},"images":[]},"colorSpace":0,"currentPageIndex":0,"foreignLayerStyles":[],"foreignSymbols":[],"foreignTextStyles":[],"layerStyles":{"_class":"sharedStyleContainer","objects":[]},"layerSymbols":{"_class":"symbolContainer","objects":[]},"layerTextStyles":{"_class":"sharedTextStyleContainer","objects":[]},"pages":[{"_class":"MSJSONFileReference","_ref_class":"MSImmutablePage","_ref":"pages\/B30266FB-B0AA-4D23-A780-F34A77F7CD6D"},{"_class":"MSJSONFileReference","_ref_class":"MSImmutablePage","_ref":"pages\/3801B73C-B16C-4822-AC31-AB47EE4788C3"}]}